Workbook

Sheet sales_data
A1: Transaction ID | B1: Order Date | C1: Customer Name | D1: Product Name | E1: Category | F1: Region | G1: Quantity | H1: Unit Price | I1: Revenue | J1: Discounted Revenue | K1: Upper | L1: LEFT | M1: MID | N1: Customer Code | O1: Product Code | P1: Cust Name Formatted | Q1: Days Since Purchase | R1: Order Month | S1: Order Age
A2: TXN001 | B2: 46194 | C2: Kabir Gupta | D2: USB Cable | E2: Electronics | F2: North | G2: 5 | H2: 142.95 | I2: =G2*H2 -> 714.75 | J2: =I2-(I2*$B$45) -> 643.275 | K2: {=UPPER(C2:C31)} -> KABIR GUPTA | L2: =LEFT(K2,2) -> KA | M2: =MID(K2,FIND(" ",K2)+1,2) -> GU | N2: =(L2&M2) -> KAGU | O2: =UPPER(LEFT(D2,3))&"-"&UPPER(LEFT(E2,2)) -> USB-EL | P2: =PROPER(C2) -> Kabir Gupta | Q2: =$B$46-B2 -> 38 | R2: =TEXT(B2, "MMM") -> Jun | S2: =PROPER(IF(Q2>30, "old order", "recent")) -> Old Order
A3: TXN002 | B3: 46211 | C3: Vivaan Menon | D3: Face Wash | E3: Beauty | F3: North | G3: 1 | H3: 197.68 | I3: =G3*H3 -> 197.68 | J3: =I3-(I3*$B$45) -> 177.912 | K3: VIVAAN MENON | L3: =LEFT(K3,2) -> VI | M3: =MID(K3,FIND(" ",K3)+1,2) -> ME | N3: =(L3&M3) -> VIME | O3: =UPPER(LEFT(D3,3))&"-"&UPPER(LEFT(E3,2)) -> FAC-BE | P3: =PROPER(C3) -> Vivaan Menon | Q3: =$B$46-B3 -> 21 | R3: =TEXT(B3, "MMM") -> Jul | S3: =PROPER(IF(Q3>30, "old order", "recent")) -> Recent
A4: TXN003 | B4: 46178 | C4: Rohan Verma | D4: Yoga Mat | E4: Sports | F4: North | G4: 5 | H4: 672.7 | I4: =G4*H4 -> 3363.5 | J4: =I4-(I4*$B$45) -> 3027.15 | K4: ROHAN VERMA | L4: =LEFT(K4,2) -> RO | M4: =MID(K4,FIND(" ",K4)+1,2) -> VE | N4: =(L4&M4) -> ROVE | O4: =UPPER(LEFT(D4,3))&"-"&UPPER(LEFT(E4,2)) -> YOG-SP | P4: =PROPER(C4) -> Rohan Verma | Q4: =$B$46-B4 -> 54 | R4: =TEXT(B4, "MMM") -> Jun | S4: =PROPER(IF(Q4>30, "old order", "recent")) -> Old Order
A5: TXN004 | B5: 46188 | C5: Manav Kapoor | D5: USB Cable | E5: Electronics | F5: West | G5: 1 | H5: 156.1 | I5: =G5*H5 -> 156.1 | J5: =I5-(I5*$B$45) -> 140.49 | K5: MANAV KAPOOR | L5: =LEFT(K5,2) -> MA | M5: =MID(K5,FIND(" ",K5)+1,2) -> KA | N5: =(L5&M5) -> MAKA | O5: =UPPER(LEFT(D5,3))&"-"&UPPER(LEFT(E5,2)) -> USB-EL | P5: =PROPER(C5) -> Manav Kapoor | Q5: =$B$46-B5 -> 44 | R5: =TEXT(B5, "MMM") -> Jun | S5: =PROPER(IF(Q5>30, "old order", "recent")) -> Old Order
A6: TXN005 | B6: 46176 | C6: Kavya Joshi | D6: Gel Pen Set | E6: Stationery | F6: East | G6: 4 | H6: 86.8 | I6: =G6*H6 -> 347.2 | J6: =I6-(I6*$B$45) -> 312.48 | K6: KAVYA JOSHI | L6: =LEFT(K6,2) -> KA | M6: =MID(K6,FIND(" ",K6)+1,2) -> JO | N6: =(L6&M6) -> KAJO | O6: =UPPER(LEFT(D6,3))&"-"&UPPER(LEFT(E6,2)) -> GEL-ST | P6: =PROPER(C6) -> Kavya Joshi | Q6: =$B$46-B6 -> 56 | R6: =TEXT(B6, "MMM") -> Jun | S6: =PROPER(IF(Q6>30, "old order", "recent")) -> Old Order
A7: TXN006 | B7: 46181 | C7: Aditya Reddy | D7: Sketch Book | E7: Stationery | F7: North | G7: 5 | H7: 151.07 | I7: =G7*H7 -> 755.35 | J7: =I7-(I7*$B$45) -> 679.815 | K7: ADITYA REDDY | L7: =LEFT(K7,2) -> AD | M7: =MID(K7,FIND(" ",K7)+1,2) -> RE | N7: =(L7&M7) -> ADRE | O7: =UPPER(LEFT(D7,3))&"-"&UPPER(LEFT(E7,2)) -> SKE-ST | P7: =PROPER(C7) -> Aditya Reddy | Q7: =$B$46-B7 -> 51 | R7: =TEXT(B7, "MMM") -> Jun | S7: =PROPER(IF(Q7>30, "old order", "recent")) -> Old Order
A8: TXN007 | B8: 46186 | C8: Priya Verma | D8: Bluetooth Speaker | E8: Electronics | F8: North | G8: 5 | H8: 1454.92 | I8: =G8*H8 -> 7274.6 | J8: =I8-(I8*$B$45) -> 6547.14 | K8: PRIYA VERMA | L8: =LEFT(K8,2) -> PR | M8: =MID(K8,FIND(" ",K8)+1,2) -> VE | N8: =(L8&M8) -> PRVE | O8: =UPPER(LEFT(D8,3))&"-"&UPPER(LEFT(E8,2)) -> BLU-EL | P8: =PROPER(C8) -> Priya Verma | Q8: =$B$46-B8 -> 46 | R8: =TEXT(B8, "MMM") -> Jun | S8: =PROPER(IF(Q8>30, "old order", "recent")) -> Old Order
A9: TXN008 | B9: 46217 | C9: Kavya Gupta | D9: Denim Jeans | E9: Apparel | F9: West | G9: 5 | H9: 1354.01 | I9: =G9*H9 -> 6770.05 | J9: =I9-(I9*$B$45) -> 6093.045 | K9: KAVYA GUPTA | L9: =LEFT(K9,2) -> KA | M9: =MID(K9,FIND(" ",K9)+1,2) -> GU | N9: =(L9&M9) -> KAGU | O9: =UPPER(LEFT(D9,3))&"-"&UPPER(LEFT(E9,2)) -> DEN-AP | P9: =PROPER(C9) -> Kavya Gupta | Q9: =$B$46-B9 -> 15 | R9: =TEXT(B9, "MMM") -> Jul | S9: =PROPER(IF(Q9>30, "old order", "recent")) -> Recent
A10: TXN009 | B10: 46197 | C10: Ananya Patel | D10: Sketch Book | E10: Stationery | F10: South | G10: 1 | H10: 151.12 | I10: =G10*H10 -> 151.12 | J10: =I10-(I10*$B$45) -> 136.008 | K10: ANANYA PATEL | L10: =LEFT(K10,2) -> AN | M10: =MID(K10,FIND(" ",K10)+1,2) -> PA | N10: =(L10&M10) -> ANPA | O10: =UPPER(LEFT(D10,3))&"-"&UPPER(LEFT(E10,2)) -> SKE-ST | P10: =PROPER(C10) -> Ananya Patel | Q10: =$B$46-B10 -> 35 | R10: =TEXT(B10, "MMM") -> Jun | S10: =PROPER(IF(Q10>30, "old order", "recent")) -> Old Order
A11: TXN010 | B11: 46207 | C11: Pooja Nair | D11: Desk Lamp | E11: Home & Kitchen | F11: East | G11: 5 | H11: 942.17 | I11: =G11*H11 -> 4710.85 | J11: =I11-(I11*$B$45) -> 4239.765 | K11: POOJA NAIR | L11: =LEFT(K11,2) -> PO | M11: =MID(K11,FIND(" ",K11)+1,2) -> NA | N11: =(L11&M11) -> PONA | O11: =UPPER(LEFT(D11,3))&"-"&UPPER(LEFT(E11,2)) -> DES-HO | P11: =PROPER(C11) -> Pooja Nair | Q11: =$B$46-B11 -> 25 | R11: =TEXT(B11, "MMM") -> Jul | S11: =PROPER(IF(Q11>30, "old order", "recent")) -> Recent
A12: TXN011 | B12: 46181 | C12: Siddharth Gupta | D12: Sketch Book | E12: Stationery | F12: East | G12: 2 | H12: 156.5 | I12: =G12*H12 -> 313 | J12: =I12-(I12*$B$45) -> 281.7 | K12: SIDDHARTH GUPTA | L12: =LEFT(K12,2) -> SI | M12: =MID(K12,FIND(" ",K12)+1,2) -> GU | N12: =(L12&M12) -> SIGU | O12: =UPPER(LEFT(D12,3))&"-"&UPPER(LEFT(E12,2)) -> SKE-ST | P12: =PROPER(C12) -> Siddharth Gupta | Q12: =$B$46-B12 -> 51 | R12: =TEXT(B12, "MMM") -> Jun | S12: =PROPER(IF(Q12>30, "old order", "recent")) -> Old Order
A13: TXN012 | B13: 46200 | C13: Vivaan Kapoor | D13: Bluetooth Speaker | E13: Electronics | F13: East | G13: 3 | H13: 1528.27 | I13: =G13*H13 -> 4584.81 | J13: =I13-(I13*$B$45) -> 4126.329 | K13: VIVAAN KAPOOR | L13: =LEFT(K13,2) -> VI | M13: =MID(K13,FIND(" ",K13)+1,2) -> KA | N13: =(L13&M13) -> VIKA | O13: =UPPER(LEFT(D13,3))&"-"&UPPER(LEFT(E13,2)) -> BLU-EL | P13: =PROPER(C13) -> Vivaan Kapoor | Q13: =$B$46-B13 -> 32 | R13: =TEXT(B13, "MMM") -> Jun | S13: =PROPER(IF(Q13>30, "old order", "recent")) -> Old Order
A14: TXN013 | B14: 46212 | C14: Pooja Rao | D14: Desk Lamp | E14: Home & Kitchen | F14: North | G14: 1 | H14: 938.98 | I14: =G14*H14 -> 938.98 | J14: =I14-(I14*$B$45) -> 845.082 | K14: POOJA RAO | L14: =LEFT(K14,2) -> PO | M14: =MID(K14,FIND(" ",K14)+1,2) -> RA | N14: =(L14&M14) -> PORA | O14: =UPPER(LEFT(D14,3))&"-"&UPPER(LEFT(E14,2)) -> DES-HO | P14: =PROPER(C14) -> Pooja Rao | Q14: =$B$46-B14 -> 20 | R14: =TEXT(B14, "MMM") -> Jul | S14: =PROPER(IF(Q14>30, "old order", "recent")) -> Recent
... A31: TXN030 | B31: 46221 | C31: Karan Bhatt | D31: Lipstick | E31: Beauty | F31: West | G31: 6 | H31: 288.88 | I31: =G31*H31 -> 1733.28 | J31: =I31-(I31*$B$45) -> 1559.952 | K31: KARAN BHATT | L31: =LEFT(K31,2) -> KA | M31: =MID(K31,FIND(" ",K31)+1,2) -> BH | N31: =(L31&M31) -> KABH | O31: =UPPER(LEFT(D31,3))&"-"&UPPER(LEFT(E31,2)) -> LIP-BE | P31: =PROPER(C31) -> Karan Bhatt | Q31: =$B$46-B31 -> 11 | R31: =TEXT(B31, "MMM") -> Jul | S31: =PROPER(IF(Q31>30, "old order", "recent")) -> Recent
A44: Constants
A45: Discount Rate | B45: 0.1
A46: Todays Date | B46: =TODAY() -> 46232

Sheet SUMMARY
A1: Total Revenue (Discounted) | B1: Avg Order Value | C1: Total Transactions | D1: Highest Order Value | E1: Lowest Order Value
A2: =SUM(sales_data!J2:J31) -> 76528.413 | B2: =AVERAGE(sales_data!J2:J31) -> 2550.9471 | C2: =COUNT(sales_data!J2:J31) -> 30 | D2: =MAX(sales_data!J2:J31) -> 8257.68 | E2: =MIN(sales_data!J2:J31) -> 136.008
B9: Total Rev | C9: No. of Transc
A10: north | B10: =SUMIF(sales_data!F2:F31, A10, sales_data!J2:J31) -> 25646.922 | C10: =COUNTIF(sales_data!F2:F31, SUMMARY!A10) -> 8
A11: south | B11: =SUMIF(sales_data!F3:F32, A11, sales_data!J3:J32) -> 21999.42 | C11: =COUNTIF(sales_data!F3:F32, SUMMARY!A11) -> 6
A12: east | B12: =SUMIF(sales_data!F4:F33, A12, sales_data!J4:J33) -> 16821.171 | C12: =COUNTIF(sales_data!F4:F33, SUMMARY!A12) -> 8
A13: west | B13: =SUMIF(sales_data!F5:F34, A13, sales_data!J5:J34) -> 12060.9 | C13: =COUNTIF(sales_data!F5:F34, SUMMARY!A13) -> 8
A15: Max revenue is in north
