Workbook

Sheet employee_data
A1: Employee ID | B1: Name | C1: Department | D1: Basic Salary | E1: Years of Service | F1: Performance Rating | G1: Attendance % | H1: Annual Basic Salary | I1: Basic Salary per day | J1: Basic salary per hour | K1: Years of Service(Months) | L1: HRA AMT | M1: DA AMT | N1: CONVEYANCE AMT | O1: GROSS SALARY | P1: PF DEDUCTION | Q1: PROFESSIONAL TAX | R1: BONUS | S1: ATTENDANCE DEDUCTION | T1: INCREMENT ELIGIBILITY | U1: SPECIAL ALLOWANCE | V1: Performance Warning Flag | W1: HIGH EARNER | X1: NET SALARY | AA1: company rates
A2: EMP001 | B2: Ishaan Gupta | C2: HR | D2: 48000 | E2: 10 | F2: 3 | G2: 95 | H2: =D2*12 -> 576000 | I2: =D2/30 -> 1600 | J2: =I2/8 -> 200 | K2: =E2*12 -> 120 | L2: =D2*$AB$2 -> 19200 | M2: =D2*$AB$3 -> 4800 | N2: =D2*$AB$4 -> 2400 | O2: =D2+L2+M2+N2 -> 74400 | P2: =D2*$AB$5 -> 5760 | Q2: =IF(O2>50000,200,IF(O2>25000,150,0)) -> 200 | R2: =IF(F2>=4,D2*10%,IF(F2=3,D2*5%,0)) -> 2400 | S2: =IF(G2<90,O2*5%,0) -> 0 | T2: =IF(AND(G2>=90,F2>=3),"Elligible","Not Elligible") -> Elligible | U2: =IF(OR(C2="Sales", C2 ="Support"),1000,0) -> 0 | V2: =IF(AND(F2<=2,K2>=3),"Needs Review","OK") -> OK | W2: =IF(OR(O2>60000,R2>5000),"High Earner","Standard") -> High Earner | X2: =O2+R2+U2-P2-Q2-S2 -> 70840 | AA2: HRA | AB2: 0.4
A3: EMP002 | B3: Meera Chauhan | C3: Engineering | D3: 55000 | E3: 2 | F3: 5 | G3: 96 | H3: =D3*12 -> 660000 | I3: =D3/30 -> 1833.3333 | J3: =I3/8 -> 229.16667 | K3: =E3*12 -> 24 | L3: =D3*$AB$2 -> 22000 | M3: =D3*$AB$3 -> 5500 | N3: =D3*$AB$4 -> 2750 | O3: =D3+L3+M3+N3 -> 85250 | P3: =D3*$AB$5 -> 6600 | Q3: =IF(O3>50000,200,IF(O3>25000,150,0)) -> 200 | R3: =IF(F3>=4,D3*10%,IF(F3=3,D3*5%,0)) -> 5500 | S3: =IF(G3<90,O3*5%,0) -> 0 | T3: =IF(AND(G3>=90,F3>=3),"Elligible","Not Elligible") -> Elligible | U3: =IF(OR(C3="Sales", C3 ="Support"),1000,0) -> 0 | V3: =IF(AND(F3<=2,K3>=3),"Needs Review","OK") -> OK | W3: =IF(OR(O3>60000,R3>5000),"High Earner","Standard") -> High Earner | X3: =O3+R3+U3-P3-Q3-S3 -> 83950 | AA3: DA | AB3: 0.1
A4: EMP003 | B4: Rohan Chauhan | C4: Sales | D4: 28000 | E4: 5 | F4: 5 | G4: 94 | H4: =D4*12 -> 336000 | I4: =D4/30 -> 933.33333 | J4: =I4/8 -> 116.66667 | K4: =E4*12 -> 60 | L4: =D4*$AB$2 -> 11200 | M4: =D4*$AB$3 -> 2800 | N4: =D4*$AB$4 -> 1400 | O4: =D4+L4+M4+N4 -> 43400 | P4: =D4*$AB$5 -> 3360 | Q4: =IF(O4>50000,200,IF(O4>25000,150,0)) -> 150 | R4: =IF(F4>=4,D4*10%,IF(F4=3,D4*5%,0)) -> 2800 | S4: =IF(G4<90,O4*5%,0) -> 0 | T4: =IF(AND(G4>=90,F4>=3),"Elligible","Not Elligible") -> Elligible | U4: =IF(OR(C4="Sales", C4 ="Support"),1000,0) -> 1000 | V4: =IF(AND(F4<=2,K4>=3),"Needs Review","OK") -> OK | W4: =IF(OR(O4>60000,R4>5000),"High Earner","Standard") -> Standard | X4: =O4+R4+U4-P4-Q4-S4 -> 43690 | AA4: CONVEYANCE | AB4: 0.05
A5: EMP004 | B5: Aditi Iyer | C5: Marketing | D5: 38000 | E5: 11 | F5: 1 | G5: 94 | H5: =D5*12 -> 456000 | I5: =D5/30 -> 1266.6667 | J5: =I5/8 -> 158.33333 | K5: =E5*12 -> 132 | L5: =D5*$AB$2 -> 15200 | M5: =D5*$AB$3 -> 3800 | N5: =D5*$AB$4 -> 1900 | O5: =D5+L5+M5+N5 -> 58900 | P5: =D5*$AB$5 -> 4560 | Q5: =IF(O5>50000,200,IF(O5>25000,150,0)) -> 200 | R5: =IF(F5>=4,D5*10%,IF(F5=3,D5*5%,0)) -> 0 | S5: =IF(G5<90,O5*5%,0) -> 0 | T5: =IF(AND(G5>=90,F5>=3),"Elligible","Not Elligible") -> Not Elligible | U5: =IF(OR(C5="Sales", C5 ="Support"),1000,0) -> 0 | V5: =IF(AND(F5<=2,K5>=3),"Needs Review","OK") -> Needs Review | W5: =IF(OR(O5>60000,R5>5000),"High Earner","Standard") -> Standard | X5: =O5+R5+U5-P5-Q5-S5 -> 54140 | AA5: PF | AB5: 0.12
A6: EMP005 | B6: Neha Rao | C6: Engineering | D6: 28000 | E6: 5 | F6: 5 | G6: 95 | H6: =D6*12 -> 336000 | I6: =D6/30 -> 933.33333 | J6: =I6/8 -> 116.66667 | K6: =E6*12 -> 60 | L6: =D6*$AB$2 -> 11200 | M6: =D6*$AB$3 -> 2800 | N6: =D6*$AB$4 -> 1400 | O6: =D6+L6+M6+N6 -> 43400 | P6: =D6*$AB$5 -> 3360 | Q6: =IF(O6>50000,200,IF(O6>25000,150,0)) -> 150 | R6: =IF(F6>=4,D6*10%,IF(F6=3,D6*5%,0)) -> 2800 | S6: =IF(G6<90,O6*5%,0) -> 0 | T6: =IF(AND(G6>=90,F6>=3),"Elligible","Not Elligible") -> Elligible | U6: =IF(OR(C6="Sales", C6 ="Support"),1000,0) -> 0 | V6: =IF(AND(F6<=2,K6>=3),"Needs Review","OK") -> OK | W6: =IF(OR(O6>60000,R6>5000),"High Earner","Standard") -> Standard | X6: =O6+R6+U6-P6-Q6-S6 -> 42690
A7: EMP006 | B7: Diya Kapoor | C7: Support | D7: 28000 | E7: 2 | F7: 1 | G7: 82 | H7: =D7*12 -> 336000 | I7: =D7/30 -> 933.33333 | J7: =I7/8 -> 116.66667 | K7: =E7*12 -> 24 | L7: =D7*$AB$2 -> 11200 | M7: =D7*$AB$3 -> 2800 | N7: =D7*$AB$4 -> 1400 | O7: =D7+L7+M7+N7 -> 43400 | P7: =D7*$AB$5 -> 3360 | Q7: =IF(O7>50000,200,IF(O7>25000,150,0)) -> 150 | R7: =IF(F7>=4,D7*10%,IF(F7=3,D7*5%,0)) -> 0 | S7: =IF(G7<90,O7*5%,0) -> 2170 | T7: =IF(AND(G7>=90,F7>=3),"Elligible","Not Elligible") -> Not Elligible | U7: =IF(OR(C7="Sales", C7 ="Support"),1000,0) -> 1000 | V7: =IF(AND(F7<=2,K7>=3),"Needs Review","OK") -> Needs Review | W7: =IF(OR(O7>60000,R7>5000),"High Earner","Standard") -> Standard | X7: =O7+R7+U7-P7-Q7-S7 -> 38720
A8: EMP007 | B8: Aarav Das | C8: Marketing | D8: 55000 | E8: 11 | F8: 3 | G8: 94 | H8: =D8*12 -> 660000 | I8: =D8/30 -> 1833.3333 | J8: =I8/8 -> 229.16667 | K8: =E8*12 -> 132 | L8: =D8*$AB$2 -> 22000 | M8: =D8*$AB$3 -> 5500 | N8: =D8*$AB$4 -> 2750 | O8: =D8+L8+M8+N8 -> 85250 | P8: =D8*$AB$5 -> 6600 | Q8: =IF(O8>50000,200,IF(O8>25000,150,0)) -> 200 | R8: =IF(F8>=4,D8*10%,IF(F8=3,D8*5%,0)) -> 2750 | S8: =IF(G8<90,O8*5%,0) -> 0 | T8: =IF(AND(G8>=90,F8>=3),"Elligible","Not Elligible") -> Elligible | U8: =IF(OR(C8="Sales", C8 ="Support"),1000,0) -> 0 | V8: =IF(AND(F8<=2,K8>=3),"Needs Review","OK") -> OK | W8: =IF(OR(O8>60000,R8>5000),"High Earner","Standard") -> High Earner | X8: =O8+R8+U8-P8-Q8-S8 -> 81200
A9: EMP008 | B9: Pooja Iyer | C9: Marketing | D9: 65000 | E9: 0 | F9: 4 | G9: 88 | H9: =D9*12 -> 780000 | I9: =D9/30 -> 2166.6667 | J9: =I9/8 -> 270.83333 | K9: =E9*12 -> 0 | L9: =D9*$AB$2 -> 26000 | M9: =D9*$AB$3 -> 6500 | N9: =D9*$AB$4 -> 3250 | O9: =D9+L9+M9+N9 -> 100750 | P9: =D9*$AB$5 -> 7800 | Q9: =IF(O9>50000,200,IF(O9>25000,150,0)) -> 200 | R9: =IF(F9>=4,D9*10%,IF(F9=3,D9*5%,0)) -> 6500 | S9: =IF(G9<90,O9*5%,0) -> 5037.5 | T9: =IF(AND(G9>=90,F9>=3),"Elligible","Not Elligible") -> Not Elligible | U9: =IF(OR(C9="Sales", C9 ="Support"),1000,0) -> 0 | V9: =IF(AND(F9<=2,K9>=3),"Needs Review","OK") -> OK | W9: =IF(OR(O9>60000,R9>5000),"High Earner","Standard") -> High Earner | X9: =O9+R9+U9-P9-Q9-S9 -> 94212.5
A10: EMP009 | B10: Aditi Chauhan | C10: Marketing | D10: 38000 | E10: 10 | F10: 5 | G10: 100 | H10: =D10*12 -> 456000 | I10: =D10/30 -> 1266.6667 | J10: =I10/8 -> 158.33333 | K10: =E10*12 -> 120 | L10: =D10*$AB$2 -> 15200 | M10: =D10*$AB$3 -> 3800 | N10: =D10*$AB$4 -> 1900 | O10: =D10+L10+M10+N10 -> 58900 | P10: =D10*$AB$5 -> 4560 | Q10: =IF(O10>50000,200,IF(O10>25000,150,0)) -> 200 | R10: =IF(F10>=4,D10*10%,IF(F10=3,D10*5%,0)) -> 3800 | S10: =IF(G10<90,O10*5%,0) -> 0 | T10: =IF(AND(G10>=90,F10>=3),"Elligible","Not Elligible") -> Elligible | U10: =IF(OR(C10="Sales", C10 ="Support"),1000,0) -> 0 | V10: =IF(AND(F10<=2,K10>=3),"Needs Review","OK") -> OK | W10: =IF(OR(O10>60000,R10>5000),"High Earner","Standard") -> Standard | X10: =O10+R10+U10-P10-Q10-S10 -> 57940
A11: EMP010 | B11: Aditi Verma | C11: Finance | D11: 52000 | E11: 8 | F11: 4 | G11: 88 | H11: =D11*12 -> 624000 | I11: =D11/30 -> 1733.3333 | J11: =I11/8 -> 216.66667 | K11: =E11*12 -> 96 | L11: =D11*$AB$2 -> 20800 | M11: =D11*$AB$3 -> 5200 | N11: =D11*$AB$4 -> 2600 | O11: =D11+L11+M11+N11 -> 80600 | P11: =D11*$AB$5 -> 6240 | Q11: =IF(O11>50000,200,IF(O11>25000,150,0)) -> 200 | R11: =IF(F11>=4,D11*10%,IF(F11=3,D11*5%,0)) -> 5200 | S11: =IF(G11<90,O11*5%,0) -> 4030 | T11: =IF(AND(G11>=90,F11>=3),"Elligible","Not Elligible") -> Not Elligible | U11: =IF(OR(C11="Sales", C11 ="Support"),1000,0) -> 0 | V11: =IF(AND(F11<=2,K11>=3),"Needs Review","OK") -> OK | W11: =IF(OR(O11>60000,R11>5000),"High Earner","Standard") -> High Earner | X11: =O11+R11+U11-P11-Q11-S11 -> 75330
A12: EMP011 | B12: Karan Iyer | C12: Finance | D12: 48000 | E12: 4 | F12: 3 | G12: 95 | H12: =D12*12 -> 576000 | I12: =D12/30 -> 1600 | J12: =I12/8 -> 200 | K12: =E12*12 -> 48 | L12: =D12*$AB$2 -> 19200 | M12: =D12*$AB$3 -> 4800 | N12: =D12*$AB$4 -> 2400 | O12: =D12+L12+M12+N12 -> 74400 | P12: =D12*$AB$5 -> 5760 | Q12: =IF(O12>50000,200,IF(O12>25000,150,0)) -> 200 | R12: =IF(F12>=4,D12*10%,IF(F12=3,D12*5%,0)) -> 2400 | S12: =IF(G12<90,O12*5%,0) -> 0 | T12: =IF(AND(G12>=90,F12>=3),"Elligible","Not Elligible") -> Elligible | U12: =IF(OR(C12="Sales", C12 ="Support"),1000,0) -> 0 | V12: =IF(AND(F12<=2,K12>=3),"Needs Review","OK") -> OK | W12: =IF(OR(O12>60000,R12>5000),"High Earner","Standard") -> High Earner | X12: =O12+R12+U12-P12-Q12-S12 -> 70840
A13: EMP012 | B13: Siddharth Gupta | C13: Support | D13: 52000 | E13: 6 | F13: 3 | G13: 78 | H13: =D13*12 -> 624000 | I13: =D13/30 -> 1733.3333 | J13: =I13/8 -> 216.66667 | K13: =E13*12 -> 72 | L13: =D13*$AB$2 -> 20800 | M13: =D13*$AB$3 -> 5200 | N13: =D13*$AB$4 -> 2600 | O13: =D13+L13+M13+N13 -> 80600 | P13: =D13*$AB$5 -> 6240 | Q13: =IF(O13>50000,200,IF(O13>25000,150,0)) -> 200 | R13: =IF(F13>=4,D13*10%,IF(F13=3,D13*5%,0)) -> 2600 | S13: =IF(G13<90,O13*5%,0) -> 4030 | T13: =IF(AND(G13>=90,F13>=3),"Elligible","Not Elligible") -> Not Elligible | U13: =IF(OR(C13="Sales", C13 ="Support"),1000,0) -> 1000 | V13: =IF(AND(F13<=2,K13>=3),"Needs Review","OK") -> OK | W13: =IF(OR(O13>60000,R13>5000),"High Earner","Standard") -> High Earner | X13: =O13+R13+U13-P13-Q13-S13 -> 73730
A14: EMP013 | B14: Pooja Sharma | C14: Engineering | D14: 32000 | E14: 8 | F14: 5 | G14: 100 | H14: =D14*12 -> 384000 | I14: =D14/30 -> 1066.6667 | J14: =I14/8 -> 133.33333 | K14: =E14*12 -> 96 | L14: =D14*$AB$2 -> 12800 | M14: =D14*$AB$3 -> 3200 | N14: =D14*$AB$4 -> 1600 | O14: =D14+L14+M14+N14 -> 49600 | P14: =D14*$AB$5 -> 3840 | Q14: =IF(O14>50000,200,IF(O14>25000,150,0)) -> 150 | R14: =IF(F14>=4,D14*10%,IF(F14=3,D14*5%,0)) -> 3200 | S14: =IF(G14<90,O14*5%,0) -> 0 | T14: =IF(AND(G14>=90,F14>=3),"Elligible","Not Elligible") -> Elligible | U14: =IF(OR(C14="Sales", C14 ="Support"),1000,0) -> 0 | V14: =IF(AND(F14<=2,K14>=3),"Needs Review","OK") -> OK | W14: =IF(OR(O14>60000,R14>5000),"High Earner","Standard") -> Standard | X14: =O14+R14+U14-P14-Q14-S14 -> 48810
A15: EMP014 | B15: Siddharth Patel | C15: Finance | D15: 60000 | E15: 5 | F15: 5 | G15: 97 | H15: =D15*12 -> 720000 | I15: =D15/30 -> 2000 | J15: =I15/8 -> 250 | K15: =E15*12 -> 60 | L15: =D15*$AB$2 -> 24000 | M15: =D15*$AB$3 -> 6000 | N15: =D15*$AB$4 -> 3000 | O15: =D15+L15+M15+N15 -> 93000 | P15: =D15*$AB$5 -> 7200 | Q15: =IF(O15>50000,200,IF(O15>25000,150,0)) -> 200 | R15: =IF(F15>=4,D15*10%,IF(F15=3,D15*5%,0)) -> 6000 | S15: =IF(G15<90,O15*5%,0) -> 0 | T15: =IF(AND(G15>=90,F15>=3),"Elligible","Not Elligible") -> Elligible | U15: =IF(OR(C15="Sales", C15 ="Support"),1000,0) -> 0 | V15: =IF(AND(F15<=2,K15>=3),"Needs Review","OK") -> OK | W15: =IF(OR(O15>60000,R15>5000),"High Earner","Standard") -> High Earner | X15: =O15+R15+U15-P15-Q15-S15 -> 91600
A16: EMP015 | B16: Diya Iyer | C16: HR | D16: 35000 | E16: 10 | F16: 3 | G16: 92 | H16: =D16*12 -> 420000 | I16: =D16/30 -> 1166.6667 | J16: =I16/8 -> 145.83333 | K16: =E16*12 -> 120 | L16: =D16*$AB$2 -> 14000 | M16: =D16*$AB$3 -> 3500 | N16: =D16*$AB$4 -> 1750 | O16: =D16+L16+M16+N16 -> 54250 | P16: =D16*$AB$5 -> 4200 | Q16: =IF(O16>50000,200,IF(O16>25000,150,0)) -> 200 | R16: =IF(F16>=4,D16*10%,IF(F16=3,D16*5%,0)) -> 1750 | S16: =IF(G16<90,O16*5%,0) -> 0 | T16: =IF(AND(G16>=90,F16>=3),"Elligible","Not Elligible") -> Elligible | U16: =IF(OR(C16="Sales", C16 ="Support"),1000,0) -> 0 | V16: =IF(AND(F16<=2,K16>=3),"Needs Review","OK") -> OK | W16: =IF(OR(O16>60000,R16>5000),"High Earner","Standard") -> Standard | X16: =O16+R16+U16-P16-Q16-S16 -> 51600
A17: EMP016 | B17: Priya Chauhan | C17: Finance | D17: 42000 | E17: 3 | F17: 1 | G17: 85 | H17: =D17*12 -> 504000 | I17: =D17/30 -> 1400 | J17: =I17/8 -> 175 | K17: =E17*12 -> 36 | L17: =D17*$AB$2 -> 16800 | M17: =D17*$AB$3 -> 4200 | N17: =D17*$AB$4 -> 2100 | O17: =D17+L17+M17+N17 -> 65100 | P17: =D17*$AB$5 -> 5040 | Q17: =IF(O17>50000,200,IF(O17>25000,150,0)) -> 200 | R17: =IF(F17>=4,D17*10%,IF(F17=3,D17*5%,0)) -> 0 | S17: =IF(G17<90,O17*5%,0) -> 3255 | T17: =IF(AND(G17>=90,F17>=3),"Elligible","Not Elligible") -> Not Elligible | U17: =IF(OR(C17="Sales", C17 ="Support"),1000,0) -> 0 | V17: =IF(AND(F17<=2,K17>=3),"Needs Review","OK") -> Needs Review | W17: =IF(OR(O17>60000,R17>5000),"High Earner","Standard") -> High Earner | X17: =O17+R17+U17-P17-Q17-S17 -> 56605
... A21: EMP020 | B21: Rohan Patel | C21: Marketing | D21: 55000 | E21: 1 | F21: 4 | G21: 94 | H21: =D21*12 -> 660000 | I21: =D21/30 -> 1833.3333 | J21: =I21/8 -> 229.16667 | K21: =E21*12 -> 12 | L21: =D21*$AB$2 -> 22000 | M21: =D21*$AB$3 -> 5500 | N21: =D21*$AB$4 -> 2750 | O21: =D21+L21+M21+N21 -> 85250 | P21: =D21*$AB$5 -> 6600 | Q21: =IF(O21>50000,200,IF(O21>25000,150,0)) -> 200 | R21: =IF(F21>=4,D21*10%,IF(F21=3,D21*5%,0)) -> 5500 | S21: =IF(G21<90,O21*5%,0) -> 0 | T21: =IF(AND(G21>=90,F21>=3),"Elligible","Not Elligible") -> Elligible | U21: =IF(OR(C21="Sales", C21 ="Support"),1000,0) -> 0 | V21: =IF(AND(F21<=2,K21>=3),"Needs Review","OK") -> OK | W21: =IF(OR(O21>60000,R21>5000),"High Earner","Standard") -> High Earner | X21: =O21+R21+U21-P21-Q21-S21 -> 83950

Sheet Projection
A1: Employee ID | B1: Name | C1: Basic Salary | D1: Year 1 | E1: Year 2 | F1: Year 3 | G1: Year 4 | H1: Year 5 | L1: ANNUAL INCREMENT RATE | M1: 0.06
D2: 1 | E2: 2 | F2: 3 | G2: 4 | H2: 5
A3: =employee_data!A2 -> EMP001 | B3: =employee_data!B2 -> Ishaan Gupta | C3: =employee_data!D2 -> 48000 | D3: =$C3*(1+$M$1*D$2) -> 50880 | E3: =$C3*(1+$M$1*E$2) -> 53760 | F3: =$C3*(1+$M$1*F$2) -> 56640 | G3: =$C3*(1+$M$1*G$2) -> 59520 | H3: =$C3*(1+$M$1*H$2) -> 62400
A4: =employee_data!A3 -> EMP002 | B4: =employee_data!B3 -> Meera Chauhan | C4: =employee_data!D3 -> 55000 | D4: =$C4*(1+$M$1*D$2) -> 58300 | E4: =$C4*(1+$M$1*E$2) -> 61600 | F4: =$C4*(1+$M$1*F$2) -> 64900 | G4: =$C4*(1+$M$1*G$2) -> 68200 | H4: =$C4*(1+$M$1*H$2) -> 71500
A5: =employee_data!A4 -> EMP003 | B5: =employee_data!B4 -> Rohan Chauhan | C5: =employee_data!D4 -> 28000 | D5: =$C5*(1+$M$1*D$2) -> 29680 | E5: =$C5*(1+$M$1*E$2) -> 31360 | F5: =$C5*(1+$M$1*F$2) -> 33040 | G5: =$C5*(1+$M$1*G$2) -> 34720 | H5: =$C5*(1+$M$1*H$2) -> 36400
A6: =employee_data!A5 -> EMP004 | B6: =employee_data!B5 -> Aditi Iyer | C6: =employee_data!D5 -> 38000 | D6: =$C6*(1+$M$1*D$2) -> 40280 | E6: =$C6*(1+$M$1*E$2) -> 42560 | F6: =$C6*(1+$M$1*F$2) -> 44840 | G6: =$C6*(1+$M$1*G$2) -> 47120 | H6: =$C6*(1+$M$1*H$2) -> 49400
A7: =employee_data!A6 -> EMP005 | B7: =employee_data!B6 -> Neha Rao | C7: =employee_data!D6 -> 28000 | D7: =$C7*(1+$M$1*D$2) -> 29680 | E7: =$C7*(1+$M$1*E$2) -> 31360 | F7: =$C7*(1+$M$1*F$2) -> 33040 | G7: =$C7*(1+$M$1*G$2) -> 34720 | H7: =$C7*(1+$M$1*H$2) -> 36400
A8: =employee_data!A7 -> EMP006 | B8: =employee_data!B7 -> Diya Kapoor | C8: =employee_data!D7 -> 28000 | D8: =$C8*(1+$M$1*D$2) -> 29680 | E8: =$C8*(1+$M$1*E$2) -> 31360 | F8: =$C8*(1+$M$1*F$2) -> 33040 | G8: =$C8*(1+$M$1*G$2) -> 34720 | H8: =$C8*(1+$M$1*H$2) -> 36400
A9: =employee_data!A8 -> EMP007 | B9: =employee_data!B8 -> Aarav Das | C9: =employee_data!D8 -> 55000 | D9: =$C9*(1+$M$1*D$2) -> 58300 | E9: =$C9*(1+$M$1*E$2) -> 61600 | F9: =$C9*(1+$M$1*F$2) -> 64900 | G9: =$C9*(1+$M$1*G$2) -> 68200 | H9: =$C9*(1+$M$1*H$2) -> 71500
A10: =employee_data!A9 -> EMP008 | B10: =employee_data!B9 -> Pooja Iyer | C10: =employee_data!D9 -> 65000 | D10: =$C10*(1+$M$1*D$2) -> 68900 | E10: =$C10*(1+$M$1*E$2) -> 72800 | F10: =$C10*(1+$M$1*F$2) -> 76700 | G10: =$C10*(1+$M$1*G$2) -> 80600 | H10: =$C10*(1+$M$1*H$2) -> 84500
A11: =employee_data!A10 -> EMP009 | B11: =employee_data!B10 -> Aditi Chauhan | C11: =employee_data!D10 -> 38000 | D11: =$C11*(1+$M$1*D$2) -> 40280 | E11: =$C11*(1+$M$1*E$2) -> 42560 | F11: =$C11*(1+$M$1*F$2) -> 44840 | G11: =$C11*(1+$M$1*G$2) -> 47120 | H11: =$C11*(1+$M$1*H$2) -> 49400
A12: =employee_data!A11 -> EMP010 | B12: =employee_data!B11 -> Aditi Verma | C12: =employee_data!D11 -> 52000 | D12: =$C12*(1+$M$1*D$2) -> 55120 | E12: =$C12*(1+$M$1*E$2) -> 58240 | F12: =$C12*(1+$M$1*F$2) -> 61360 | G12: =$C12*(1+$M$1*G$2) -> 64480 | H12: =$C12*(1+$M$1*H$2) -> 67600
A13: =employee_data!A12 -> EMP011 | B13: =employee_data!B12 -> Karan Iyer | C13: =employee_data!D12 -> 48000 | D13: =$C13*(1+$M$1*D$2) -> 50880 | E13: =$C13*(1+$M$1*E$2) -> 53760 | F13: =$C13*(1+$M$1*F$2) -> 56640 | G13: =$C13*(1+$M$1*G$2) -> 59520 | H13: =$C13*(1+$M$1*H$2) -> 62400
A14: =employee_data!A13 -> EMP012 | B14: =employee_data!B13 -> Siddharth Gupta | C14: =employee_data!D13 -> 52000 | D14: =$C14*(1+$M$1*D$2) -> 55120 | E14: =$C14*(1+$M$1*E$2) -> 58240 | F14: =$C14*(1+$M$1*F$2) -> 61360 | G14: =$C14*(1+$M$1*G$2) -> 64480 | H14: =$C14*(1+$M$1*H$2) -> 67600
... A22: =employee_data!A21 -> EMP020 | B22: =employee_data!B21 -> Rohan Patel | C22: =employee_data!D21 -> 55000 | D22: =$C22*(1+$M$1*D$2) -> 58300 | E22: =$C22*(1+$M$1*E$2) -> 61600 | F22: =$C22*(1+$M$1*F$2) -> 64900 | G22: =$C22*(1+$M$1*G$2) -> 68200 | H22: =$C22*(1+$M$1*H$2) -> 71500

Sheet Summary
A2: METRIC | B2: VALUE
A3: TOTAL MONTHLY PAYROLL | B3: =SUM(employee_data!X2:X21) -> 1362860
A4: AVERAGE NET SALARY | B4: =AVERAGE(employee_data!X2:X21) -> 68143
A5: HIGHEST NET SALARY | B5: =MAX(employee_data!X2:X21) -> 94212.5
A6: LOWEST NET SALARY | B6: =MIN(employee_data!X2:X21) -> 38720
A7: Eligible for Inc. | B7: =COUNTIF(employee_data!T2:T21,"Elligible") -> 12
A10: AVERAGE NET SALARY BY DEPARTMENT | B10: Column1
A11: DEPARTMENT | B11: AVERAGE
A12: Sales | B12: =AVERAGEIF(employee_data!C2:C21,A12,employee_data!X2:X21) -> 43690
A13: Marketing | B13: =AVERAGEIF(employee_data!C3:C22,A13,employee_data!X3:X22) -> 73313.75
A14: Support | B14: =AVERAGEIF(employee_data!C4:C23,A14,employee_data!X4:X23) -> 64270
A15: Engineering | B15: =AVERAGEIF(employee_data!C5:C24,A15,employee_data!X5:X24) -> 45750
A16: Finance | B16: =AVERAGEIF(employee_data!C6:C25,A16,employee_data!X6:X25) -> 77717.5
A17: HR | B17: =AVERAGEIF(employee_data!C7:C26,A17,employee_data!X7:X26) -> 51600
A20: Performance Rating Breakdown
A21: Rating | B21: Count
A22: 1 | B22: =COUNTIF(employee_data!$F$2:$F$21,A22) -> 3
A23: 2 | B23: =COUNTIF(employee_data!$F$2:$F$21,A23) -> 1
A24: 3 | B24: =COUNTIF(employee_data!$F$2:$F$21,A24) -> 5
A25: 4 | B25: =COUNTIF(employee_data!$F$2:$F$21,A25) -> 5
A26: 5 | B26: =COUNTIF(employee_data!$F$2:$F$21,A26) -> 6

Sheet Fix This 
A1: Department Bonus Pool — Fix the Broken Formulas Below
A3: Each row below contains a formula that a previous analyst wrote, but something went wrong. Diagnose the error, then rewrite each formula correctly using the raw data provided in columns G:I.
G4: Raw Data for Reference
A5: Department | B5: Total Basic Salary | C5: Bonus Pool (10%) | D5: Avg Bonus / Employee | E5: Error Diagnosis (fill in) | G5: Department | H5: Basic Salary | I5: Employee Count
A6: Sales | B6: =SUM(H6:H23) -> 831000 | C6: =B6*0.1 -> 83100 | D6: =C6/1 -> 83100 | E6: Diagnose: what does #REF! mean, and how did this likely happen? It appears when a formula refers to a cell or range that no longer exists. | G6: Sales | H6: 28000 | I6: 1
A7: Marketing | B7: =SUMIF($G$7:$G$23,A7,$H$7:$H$23) -> 206000 | C7: =B7*0.1 -> 20600 | D7: =C7/SUM(I7:I10) -> 2575 | E7: Diagnose: why does this formula return #DIV/0!, and which cell is the real problem? divide by zero | G7: Marketing | H7: 38000 | I7: 5
A8: Support | B8: =SUMIF($G$7:$G$23,A8,$H$7:$H$23) -> 132000 | C8: =B8*0.1 -> 13200 | D8: =C8/3 -> 4400 | E8: Diagnose: what's wrong with the function name used in B8? Not Summ but Sum and @ not required | G8: Marketing | H8: 55000 | I8: 1
A9: Engineering | B9: =SUMIF($G$7:$G$23,A9,$H$7:$H$23) -> 115000 | C9: =B9*0.1 -> 11500 | D9: =C9/3 -> 3833.3333 | E9: Diagnose: why does B9 return #VALUE!, and what does that error category mean? turns #VALUE! because you're trying to add text ("N/A") to numbers. | G9: Marketing | H9: 65000 | I9: 1
A10: Finance | B10: =SUMIF($G$7:$G$23,A10,$H$7:$H$23) -> 267000 | C10: =B10*0.1 -> 26700 | D10: =C10/5 -> 5340 | E10: Diagnose: this one shows a number, not an error — but is the range actually correct? Check it against the raw data. Range Incorrect | G10: Marketing | H10: 48000 | I10: 1
G11: Support | H11: 28000 | I11: 1
G12: Support | H12: 52000 | I12: 2
G13: Support | H13: 52000 | I13: 0
G14: Engineering | H14: 55000 | I14: 1
G15: Engineering | H15: 28000 | I15: 1
G16: Engineering | H16: 32000 | I16: 1
G17: Finance | H17: 52000 | I17: 1
G18: Finance | H18: 48000 | I18: 1
G19: Finance | H19: 60000 | I19: 1
G20: Finance | H20: 42000 | I20: 1
G21: Finance | H21: 65000 | I21: 1
G22: HR | H22: 48000 | I22: 1
G23: HR | H23: 35000 | I23: 1

Sheet Notes
A5: Notes
A6: the embedded formula for calculating the performance warning flag using IF(AND) was the trickiest
A7: Understanding different Excel error types such as #REF!, #DIV/0!, and #VALUE!.
A8: Identifying why formulas produced errors instead of valid results.
A9: Correcting incorrect cell and range references in formulas.
A10: Using the SUMIF function with the correct syntax and arguments.
A11: Distinguishing between formula syntax errors and logical errors.
A12: Finding mistakes in function names and invalid formula operators.
A13: Debugging formulas affected by missing or deleted cell references.
A14: Handling divide-by-zero situations by checking source data.
A15: Recognizing how text values can cause #VALUE! errors in calculations.
A16: Verifying that formulas referenced the intended data range rather than simply returning a numeric result.
... A18: Improving accuracy in reading and interpreting Excel formulas before making corrections
